database_automation/__init__.py
database_automation/mongo_crud.py
mongodb_connect_hminh-0.0.5.dist-info/METADATA
mongodb_connect_hminh-0.0.5.dist-info/WHEEL
mongodb_connect_hminh-0.0.5.dist-info/top_level.txt
mongodb_connect_hminh-0.0.5.dist-info/RECORD
